PyPackExer/__init__.py
PyPackExer/add.py
PyPackExer/power.py
PyPackExer/subtract.py
PyPackExer/extras/__init__.py
PyPackExer/extras/divide.py
PyPackExer/extras/multiply.py
PyPackExer-0.0.2.dist-info/METADATA
PyPackExer-0.0.2.dist-info/WHEEL
PyPackExer-0.0.2.dist-info/top_level.txt
PyPackExer-0.0.2.dist-info/RECORD
