Metadata-Version: 2.1
Name: PyPackExer
Version: 0.0.2
Summary: My first Python package
Author: Dylan Watson
Author-email: <jwatson8@g.emporia.edu>
Keywords: python,simpleCalpackage
Classifier: Development Status :: 3 - Alpha
Classifier: Intended Audience :: Education
Classifier: Programming Language :: Python :: 2
Classifier: Programming Language :: Python :: 3
Classifier: Operating System :: MacOS :: MacOS X
Classifier: Operating System :: Microsoft :: Windows
